src/VersionUtil.py
src/__init__.py
PLZREMLA23Team09LibProject-1.0.0.dist-info/METADATA
PLZREMLA23Team09LibProject-1.0.0.dist-info/WHEEL
PLZREMLA23Team09LibProject-1.0.0.dist-info/top_level.txt
PLZREMLA23Team09LibProject-1.0.0.dist-info/RECORD
